.gitignore
MANIFEST.in
README.txt
bootstrap.py
buildout.cfg
setup.py
collective/__init__.py
collective.masonry.egg-info/PKG-INFO
collective.masonry.egg-info/SOURCES.txt
collective.masonry.egg-info/dependency_links.txt
collective.masonry.egg-info/entry_points.txt
collective.masonry.egg-info/namespace_packages.txt
collective.masonry.egg-info/not-zip-safe
collective.masonry.egg-info/requires.txt
collective.masonry.egg-info/top_level.txt
collective/masonry/__init__.py
collective/masonry/configure.zcml
collective/masonry/interfaces.py
collective/masonry/manager.py
collective/masonry/tests.py
collective/masonry/upgrades.py
collective/masonry/upgrades.zcml
collective/masonry/viewlets.py
collective/masonry/profiles/default/browserlayer.xml
collective/masonry/profiles/default/cssregistry.xml
collective/masonry/profiles/default/jsregistry.xml
collective/masonry/profiles/default/metadata.xml
collective/masonry/profiles/default/portlets.xml
collective/masonry/profiles/default/registry.xml
collective/masonry/profiles/default/skins.xml
collective/masonry/resources/masonry.css
collective/masonry/resources/masonry.js
collective/masonry/resources/masonry.less
collective/masonry/templates/manageportlets.pt
collective/masonry/templates/portletsabovecontent.pt
collective/masonry/templates/portletsbelowcontent.pt
collective/masonry/templates/renderer.pt
docs/HISTORY.txt
docs/INSTALL.txt
docs/LICENSE.GPL
docs/LICENSE.txt