Metadata-Version: 1.0
Name: collective.masonry
Version: 1.2.2
Summary: Integrate Masonry to Plone
Home-page: https://github.com/collective/collective.masonry
Author: JeanMichel FRANCOIS
Author-email: toutpt@gmail.com
License: GPL
Keywords: plone masonry
Platform: UNKNOWN
Classifier: Framework :: Plone
Classifier: Framework :: Plone :: 4.0
Classifier: Framework :: Plone :: 4.1
Classifier: Framework :: Plone :: 4.2
Classifier: Programming Language :: Python
